img_dlder/__init__.py
img_dlder/img_dlder.py
img_dlder-0.0.1.dist-info/METADATA
img_dlder-0.0.1.dist-info/WHEEL
img_dlder-0.0.1.dist-info/RECORD
